np_datajoint/__init__.py
np_datajoint/classes.py
np_datajoint/comparisons.py
np_datajoint/config.py
np_datajoint/hpc/slurm_launcher.py
np_datajoint/hpc/upload_session.py
np_datajoint/utils.py
np_datajoint/widgets.py
np_datajoint-0.0.6.dist-info/METADATA
np_datajoint-0.0.6.dist-info/WHEEL
np_datajoint-0.0.6.dist-info/RECORD
